rql/parser.g
rql/rql_solve.cpython-38-x86_64-linux-gnu.so
rql/_exceptions.py
rql/nodes.py
rql/stcheck.py
rql/base.py
rql/utils.py
rql/stmts.py
rql/gecode_solver.cpp
rql/interfaces.py
rql/undo.py
rql/py.typed
rql/analyze.py
rql/__init__.py
rql/parser/__main__.py
rql/parser/__init__.py
rql-1.0.2.dist-info/METADATA
rql-1.0.2.dist-info/RECORD
rql-1.0.2.dist-info/WHEEL
rql-1.0.2.dist-info/COPYING.LESSER
rql-1.0.2.dist-info/top_level.txt
rql-1.0.2.dist-info/COPYING
rql.libs/libgecodesupport-87bccb56.so.49.0
rql.libs/libgecodeint-b9475a4f.so.49.0
rql.libs/libgecodekernel-b7e07cd0.so.49.0
rql.libs/libgecodesearch-9d3c2e85.so.49.0
