Metadata-Version: 2.1
Name: rql
Version: 1.0.2
Summary: relationship query language (RQL) utilities
Home-page: https://forge.extranet.logilab.fr/CubicWeb/RQL/
Author: Logilab
Author-email: contact@logilab.fr
License: LGPL
Classifier: License :: OSI Approved :: GNU Lesser General Public License v2 or later (LGPLv2+)
Classifier: Programming Language :: Python
Classifier: Programming Language :: Python :: 3
Classifier: Programming Language :: Python :: 3 :: Only
Classifier: Topic :: Database
Classifier: Topic :: Software Development :: Libraries :: Python Modules
Requires-Python: >=3.7
License-File: COPYING
License-File: COPYING.LESSER
Requires-Dist: logilab-common (<3.0.0,>=2.0.0)
Requires-Dist: logilab-database (<3.0.0,>=2.0.0)
Requires-Dist: yapps2-logilab (>=2.2.1)
Requires-Dist: logilab-constraint (<2.0.0,>=1.0.0)
Requires-Dist: setuptools
Requires-Dist: importlib-metadata ; python_version < "3.10"
Requires-Dist: typing-extensions ; python_version < "3.8"
